{
  "annotations": {
    "list": [
      {
        "builtIn": 1,
        "datasource": {
          "type": "grafana",
          "uid": "-- Grafana --"
        },
        "enable": true,
        "hide": true,
        "iconColor": "rgba(0, 211, 255, 1)",
        "name": "Annotations & Alerts",
        "type": "dashboard"
      }
    ]
  },
  "editable": true,
  "fiscalYearStartMonth": 0,
  "graphTooltip": 0,
  "id": null,
  "links": [],
  "panels": [
    {
      "datasource": {
        "type": "prometheus",
        "uid": "prometheus"
      },
      "fieldConfig": {
        "defaults": {
          "color": {
            "mode": "thresholds"
          },
          "mappings": [
            {
              "options": {
                "0": {
                  "color": "red",
                  "index": 0,
                  "text": "DOWN"
                },
                "1": {
                  "color": "green",
                  "index": 1,
                  "text": "UP"
                }
              },
              "type": "value"
            }
          ],
          "thresholds": {
            "mode": "absolute",
            "steps": [
              {
                "color": "red",
                "value": null
              },
              {
                "color": "green",
                "value": 1
              }
            ]
          }
        },
        "overrides": []
      },
      "gridPos": {
        "h": 8,
        "w": 6,
        "x": 0,
        "y": 0
      },
      "id": 1,
      "options": {
        "colorMode": "background",
        "graphMode": "none",
        "justifyMode": "center",
        "orientation": "auto",
        "reduceOptions": {
          "calcs": [
            "lastNotNull"
          ],
          "fields": "",
          "values": false
        },
        "textMode": "value_and_name"
      },
      "pluginVersion": "11.1.0",
      "targets": [
        {
          "editorMode": "code",
          "expr": "up{job=\"orchestrator\"}",
          "legendFormat": "{{instance}}",
          "range": true,
          "refId": "A"
        }
      ],
      "title": "Orchestrator Up",
      "type": "stat"
    },
    {
      "datasource": {
        "type": "prometheus",
        "uid": "prometheus"
      },
      "fieldConfig": {
        "defaults": {
          "color": {
            "mode": "palette-classic"
          },
          "unit": "short"
        },
        "overrides": []
      },
      "gridPos": {
        "h": 8,
        "w": 9,
        "x": 6,
        "y": 0
      },
      "id": 2,
      "options": {
        "legend": {
          "calcs": [],
          "displayMode": "list",
          "placement": "bottom",
          "showLegend": true
        },
        "tooltip": {
          "mode": "single",
          "sort": "none"
        }
      },
      "pluginVersion": "11.1.0",
      "targets": [
        {
          "editorMode": "code",
          "expr": "go_goroutines",
          "legendFormat": "{{job}}",
          "range": true,
          "refId": "A"
        }
      ],
      "title": "Go Goroutines",
      "type": "timeseries"
    },
    {
      "datasource": {
        "type": "prometheus",
        "uid": "prometheus"
      },
      "fieldConfig": {
        "defaults": {
          "color": {
            "mode": "palette-classic"
          },
          "unit": "s"
        },
        "overrides": []
      },
      "gridPos": {
        "h": 8,
        "w": 9,
        "x": 15,
        "y": 0
      },
      "id": 3,
      "options": {
        "legend": {
          "calcs": [],
          "displayMode": "list",
          "placement": "bottom",
          "showLegend": true
        },
        "tooltip": {
          "mode": "single",
          "sort": "none"
        }
      },
      "pluginVersion": "11.1.0",
      "targets": [
        {
          "editorMode": "code",
          "expr": "rate(process_cpu_seconds_total[1m])",
          "legendFormat": "{{job}}",
          "range": true,
          "refId": "A"
        }
      ],
      "title": "CPU Usage (rate 1m)",
      "type": "timeseries"
    }
  ],
  "refresh": "5s",
  "schemaVersion": 39,
  "tags": [
    "orchestrator",
    "prometheus"
  ],
  "templating": {
    "list": []
  },
  "time": {
    "from": "now-15m",
    "to": "now"
  },
  "timepicker": {},
  "timezone": "",
  "title": "Orchestrator Overview",
  "uid": "orchestrator-overview",
  "version": 1,
  "weekStart": ""
}
